kistipy/__init__.py
kistipy/sdk/__init__.py
kistipy/sdk/metadata/__init__.py
kistipy/sdk/metadata/store.py
kistipy/sdk/type/__init__.py
kistipy/sdk/type/common.py
kistipy-0.0.6.dist-info/METADATA
kistipy-0.0.6.dist-info/WHEEL
kistipy-0.0.6.dist-info/top_level.txt
kistipy-0.0.6.dist-info/RECORD
