Metadata-Version: 2.1
Name: kistipy
Version: 0.0.6
Summary: kistipy
Home-page: https://github.com/prosopher/kistipy
Author: prosopher
Author-email: prosopher@gmail.com
License: UNKNOWN
Platform: UNKNOWN
Classifier: Programming Language :: Python :: 3
Classifier: Operating System :: OS Independent
Requires-Python: >=3.9.12
Requires-Dist: datasets
Requires-Dist: numpy
Requires-Dist: pandas
